{"cameraMode":{"drawMode":0,"name":"Shaded","section":"Shading Mode"},"sceneLighting":true,"audioPlay":false,"sceneViewState":{"m_AlwaysRefresh":false,"showFog":true,"showSkybox":true,"showFlares":true,"showImageEffects":true,"showParticleSystems":true,"showVisualEffectGraphs":true,"m_FxEnabled":true},"in2DMode":false,"pivot":{"x":-333.1092529296875,"y":70.90352630615235,"z":2.6876213550567629},"rotation":{"x":0.28439655900001528,"y":0.42159080505371096,"z":-0.14062067866325379,"w":0.8495886325836182},"size":1.6038315296173096,"orthographic":false}